README.md
setup.py
libtsne/__init__.py
libtsne/libtsne.py
libtsne.egg-info/PKG-INFO
libtsne.egg-info/SOURCES.txt
libtsne.egg-info/dependency_links.txt
libtsne.egg-info/top_level.txt